Metadata-Version: 2.1
Name: var_procesor
Version: 0.0.1
Summary: Var_processor is a Python library that can automatically handle common variable operations in projects.
Home-page: https://github.com/Yu-Jie1669/var_procesor
Author: Yj Lin
Author-email: yjlin2001@gmail.com
Classifier: Programming Language :: Python :: 3
Classifier: License :: OSI Approved :: MIT License
Classifier: Operating System :: OS Independent
Requires-Python: >=3.6
License-File: LICENSE
Requires-Dist: numpy
Requires-Dist: torch
